{"rows":[{"id":"1","name":"8114C","markerimage":"imagen/bus_taller.png","ruta":"LIMCHI","nocupa":"52","tocupa":"17","tlibres":"35","fecha":"29/03/2016 15:39:17","trama":"Taller Sta Anita","vel":"0","lat":"-12.055","lng":"-76.97194"},{"id":"2","name":"8108C","markerimage":"imagen/bus_taller.png","ruta":"______","nocupa":"52","tocupa":"0","tlibres":"52","fecha":"29/03/2016 15:39:31","trama":"Taller Sta Anita","vel":"0","lat":"-12.05444","lng":"-76.97083"},{"id":"3","name":"8104C","markerimage":"imagen/busde.png","ruta":"LIMCAJ","nocupa":"52","tocupa":"40","tlibres":"12","fecha":"29/03/2016 15:39:52","trama":"Trama Normal","vel":"0","lat":"-12.08417","lng":"-77.00444"},{"id":"4","name":"8122C","markerimage":"imagen/bus_taller.png","ruta":"AQPLIM","nocupa":"52","tocupa":"18","tlibres":"34","fecha":"29/03/2016 15:39:24","trama":"Taller Arequipa","vel":"0","lat":"-16.40694","lng":"-71.56111"},{"id":"5","name":"8126C","markerimage":"imagen/busde.png","ruta":"LIMAQP","nocupa":"52","tocupa":"33","tlibres":"19","fecha":"29/03/2016 15:39:46","trama":"Trama Normal","vel":"90","lat":"-12.495","lng":"-76.74333"},{"id":"6","name":"8132C","markerimage":"imagen/busde_age.png","ruta":"CHILIM","nocupa":"52","tocupa":"43","tlibres":"9","fecha":"29/03/2016 15:39:29","trama":"Terminal Chiclayo","vel":"0","lat":"-6.77611","lng":"-79.83694"},{"id":"7","name":"8134C","markerimage":"imagen/busde_age.png","ruta":"______","nocupa":"52","tocupa":"0","tlibres":"52","fecha":"29/03/2016 15:39:27","trama":"Ag.huancayo(ferrocarril)","vel":"0","lat":"-12.06028","lng":"-75.20917"},{"id":"8","name":"8138C","markerimage":"imagen/busiz.png","ruta":"LIMTUM","nocupa":"52","tocupa":"35","tlibres":"17","fecha":"29/03/2016 15:43:38","trama":"Trama Normal","vel":"32","lat":"-11.71417","lng":"-77.18167"},{"id":"9","name":"8102C","markerimage":"imagen/bus_taller.png","ruta":"______","nocupa":"52","tocupa":"0","tlibres":"52","fecha":"29/03/2016 15:39:18","trama":"Taller Sta Anita","vel":"0","lat":"-12.05528","lng":"-76.97194"},{"id":"10","name":"8106C","markerimage":"imagen/busde_age.png","ruta":"HUNLIM","nocupa":"52","tocupa":"16","tlibres":"36","fecha":"29/03/2016 15:39:20","trama":"Ag.huancayo(ferrocarril)","vel":"0","lat":"-12.06028","lng":"-75.20917"},{"id":"11","name":"8136C","markerimage":"imagen/bus_sprg.png","ruta":"______","nocupa":"52","tocupa":"0","tlibres":"52","fecha":"29/03/2016 15:43:08","trama":"Trama Normal","vel":"0","lat":"-12.06778","lng":"-76.98028"},{"id":"12","name":"8110C","markerimage":"imagen/busde_ret.png","ruta":"TUMLIM","nocupa":"52","tocupa":"43","tlibres":"9","fecha":"29/03/2016 15:39:31","trama":"Trama Normal","vel":"0","lat":"-3.66806","lng":"-80.64639"},{"id":"13","name":"8116C","markerimage":"imagen/busde_age.png","ruta":"______","nocupa":"52","tocupa":"0","tlibres":"52","fecha":"29/03/2016 15:39:54","trama":"Ag.trujillo","vel":"0","lat":"-8.10389","lng":"-79.02361"},{"id":"14","name":"8124C","markerimage":"imagen/bus_taller.png","ruta":"LIMAQP","nocupa":"52","tocupa":"45","tlibres":"7","fecha":"29/03/2016 15:39:19","trama":"Taller Sta Anita","vel":"0","lat":"-12.05528","lng":"-76.97222"},{"id":"15","name":"8112C","markerimage":"imagen/bus_taller.png","ruta":"TACLIM","nocupa":"52","tocupa":"29","tlibres":"23","fecha":"29/03/2016 15:39:29","trama":"Taller Tacna","vel":"0","lat":"-18.00556","lng":"-70.25917"},{"id":"16","name":"8118C","markerimage":"imagen/bus_taller.png","ruta":"LIMSUL","nocupa":"52","tocupa":"20","tlibres":"32","fecha":"29/03/2016 15:39:11","trama":"Taller Sta Anita","vel":"0","lat":"-12.05472","lng":"-76.97222"},{"id":"17","name":"8130C","markerimage":"imagen/bus_sprg.png","ruta":"______","nocupa":"52","tocupa":"0","tlibres":"52","fecha":"29/03/2016 15:38:56","trama":"Terrapuerto Aqp","vel":"0","lat":"-16.42389","lng":"-71.54556"},{"id":"18","name":"5084C","markerimage":"imagen/bus_taller_rtx.png","ruta":"______","nocupa":"49","tocupa":"0","tlibres":"49","fecha":"24/08/2015 15:49:31","trama":"Taller Sta Anita","vel":"7","lat":"-12.05495","lng":"-76.97101"},{"id":"19","name":"4014C","markerimage":"imagen/bus_sprg.png","ruta":"______","nocupa":"62","tocupa":"0","tlibres":"62","fecha":"29/03/2016 15:43:01","trama":"Trama Normal","vel":"0","lat":"-12.13667","lng":"-76.98083"},{"id":"20","name":"8010C","markerimage":"imagen/busde_ret.png","ruta":"NAZLIM","nocupa":"52","tocupa":"18","tlibres":"34","fecha":"29/03/2016 15:43:25","trama":"Trama Normal","vel":"55","lat":"-14.82722","lng":"-74.94889"},{"id":"21","name":"7008C","markerimage":"imagen/busde.png","ruta":"LIMQOS","nocupa":"39","tocupa":"34","tlibres":"5","fecha":"29/03/2016 15:39:11","trama":"Trama Normal","vel":"86","lat":"-12.82917","lng":"-76.52889"},{"id":"22","name":"PQ538","markerimage":"imagen/bus_taller.png","ruta":"______","nocupa":"0","tocupa":"0","tlibres":"0","fecha":"29/03/2016 15:40:31","trama":"Taller Sta Anita","vel":"0","lat":"-12.05473","lng":"-76.97203"},{"id":"23","name":"7024C","markerimage":"imagen/bus_sprg_rtx.png","ruta":"______","nocupa":"39","tocupa":"0","tlibres":"39","fecha":"29/03/2016 08:27:41","trama":"Trama Normal","vel":"0","lat":"-12.57861","lng":"-69.20111"},{"id":"24","name":"7128C","markerimage":"imagen/busde_age.png","ruta":"HUNLIM","nocupa":"39","tocupa":"18","tlibres":"21","fecha":"29/03/2016 15:43:15","trama":"Ag.huancayo(ferrocarril)","vel":"0","lat":"-12.0601","lng":"-75.2092"},{"id":"25","name":"7108C","markerimage":"imagen/busiz_ret_tx.png","ruta":"HUNLIM","nocupa":"39","tocupa":"18","tlibres":"21","fecha":"29/03/2016 14:52:01","trama":"Trama Normal","vel":"0","lat":"-12.0602","lng":"-75.20907"},{"id":"26","name":"7030C","markerimage":"imagen/busde_ret.png","ruta":"TRULIM","nocupa":"39","tocupa":"20","tlibres":"19","fecha":"29/03/2016 15:43:47","trama":"Trama Normal","vel":"0","lat":"-8.10389","lng":"-79.02389"},{"id":"27","name":"7032C","markerimage":"imagen/busde_ret.png","ruta":"TRULIM","nocupa":"39","tocupa":"20","tlibres":"19","fecha":"29/03/2016 15:43:41","trama":"Trama Normal","vel":"74","lat":"-11.02194","lng":"-77.5975"},{"id":"28","name":"7012C","markerimage":"imagen/busde_age_rtx.png","ruta":"HUNLIM","nocupa":"39","tocupa":"28","tlibres":"11","fecha":"29/03/2016 12:59:40","trama":"Ag.huancayo(ferrocarril)","vel":"0","lat":"-12.06028","lng":"-75.20917"},{"id":"29","name":"6020C","markerimage":"imagen/bus_taller_rtx.png","ruta":"______","nocupa":"49","tocupa":"0","tlibres":"49","fecha":"15/02/2016 15:31:23","trama":"Taller Ruiseñores","vel":"0","lat":"-12.05227","lng":"-76.96745"},{"id":"30","name":"6026C","markerimage":"imagen/bus_sprg.png","ruta":"______","nocupa":"49","tocupa":"0","tlibres":"49","fecha":"29/03/2016 15:40:43","trama":"Trama Normal","vel":"0","lat":"-12.05447","lng":"-76.97243"},{"id":"31","name":"4106C","markerimage":"imagen/bus_taller.png","ruta":"LIMICA","nocupa":"0","tocupa":"9","tlibres":"-9","fecha":"29/03/2016 15:40:02","trama":"Taller Sta Anita","vel":"0","lat":"-12.05486","lng":"-76.97137"},{"id":"32","name":"4108C","markerimage":"imagen/busiz_ret.png","ruta":"ICALIM","nocupa":"0","tocupa":"35","tlibres":"-35","fecha":"29/03/2016 15:40:09","trama":"Trama Normal","vel":"87","lat":"-12.74859","lng":"-76.60954"},{"id":"33","name":"8000C","markerimage":"imagen/busiz_ret.png","ruta":"GYELIM","nocupa":"52","tocupa":"29","tlibres":"23","fecha":"29/03/2016 15:34:42","trama":"Trama Normal","vel":"86","lat":"-2.57444","lng":"-79.58"},{"id":"34","name":"4026C","markerimage":"imagen/bus_sprg.png","ruta":"______","nocupa":"62","tocupa":"0","tlibres":"62","fecha":"29/03/2016 15:42:55","trama":"Trama Normal","vel":"0","lat":"-12.05444","lng":"-76.9725"},{"id":"35","name":"7028C","markerimage":"imagen/bus_nolimiz_rtx.png","ruta":"AQPCVM","nocupa":"39","tocupa":"0","tlibres":"39","fecha":"21/03/2016 10:23:55","trama":"Trama Normal","vel":"0","lat":"-16.40833","lng":"-71.55222"},{"id":"36","name":"4020C","markerimage":"imagen/bus_taller_rtx.png","ruta":"______","nocupa":"62","tocupa":"0","tlibres":"62","fecha":"29/03/2016 09:35:57","trama":"Taller Sta Anita","vel":"0","lat":"-12.055","lng":"-76.97167"},{"id":"37","name":"7006C","markerimage":"imagen/bus_taller_rtx.png","ruta":"LIMTRU","nocupa":"39","tocupa":"29","tlibres":"10","fecha":"29/03/2016 11:31:37","trama":"Taller Sta Anita","vel":"5","lat":"-12.05472","lng":"-76.97083"},{"id":"38","name":"4010C","markerimage":"imagen/bus_taller.png","ruta":"______","nocupa":"62","tocupa":"0","tlibres":"62","fecha":"29/03/2016 15:43:43","trama":"Taller Sta Anita","vel":"0","lat":"-12.05444","lng":"-76.97056"},{"id":"39","name":"4024C","markerimage":"imagen/bus_sprg.png","ruta":"______","nocupa":"62","tocupa":"0","tlibres":"62","fecha":"29/03/2016 15:43:03","trama":"Trama Normal","vel":"0","lat":"-12.05417","lng":"-76.97167"},{"id":"40","name":"5080C","markerimage":"imagen/bus_taller_rtx.png","ruta":"______","nocupa":"49","tocupa":"0","tlibres":"49","fecha":"15/02/2016 18:56:55","trama":"Taller Sta Anita","vel":"0","lat":"-12.05439","lng":"-76.97104"},{"id":"41","name":"8142C","markerimage":"imagen/busde_age.png","ruta":"CAJLIM","nocupa":"52","tocupa":"28","tlibres":"24","fecha":"29/03/2016 15:43:26","trama":"Ag.cajamarca","vel":"0","lat":"-7.16583","lng":"-78.49944"},{"id":"42","name":"5094C","markerimage":"imagen/bus_taller_rtx.png","ruta":"______","nocupa":"49","tocupa":"0","tlibres":"49","fecha":"15/02/2016 15:07:06","trama":"Taller Sta Anita","vel":"0","lat":"-12.05508","lng":"-76.97121"},{"id":"43","name":"8014C","markerimage":"imagen/bus_nolimde.png","ruta":"QOSAQP","nocupa":"52","tocupa":"18","tlibres":"34","fecha":"29/03/2016 15:43:24","trama":"Trama Normal","vel":"0","lat":"-13.53306","lng":"-71.94972"},{"id":"44","name":"8016C","markerimage":"imagen/busde_ret.png","ruta":"NAZLIM","nocupa":"52","tocupa":"27","tlibres":"25","fecha":"29/03/2016 15:43:51","trama":"Paso Por Pisco","vel":"54","lat":"-13.71444","lng":"-76.15361"},{"id":"45","name":"7034C","markerimage":"imagen/bus_taller.png","ruta":"LIMTRU","nocupa":"39","tocupa":"21","tlibres":"18","fecha":"29/03/2016 15:43:06","trama":"Taller Sta Anita","vel":"0","lat":"-12.05472","lng":"-76.97167"},{"id":"46","name":"8004C","markerimage":"imagen/busde.png","ruta":"LIMGYE","nocupa":"52","tocupa":"44","tlibres":"8","fecha":"29/03/2016 15:43:27","trama":"Migraciones Huaquillas","vel":"0","lat":"-3.49778","lng":"-80.21611"},{"id":"47","name":"5006C","markerimage":"imagen/bus_sprg_rtx.png","ruta":"______","nocupa":"49","tocupa":"0","tlibres":"49","fecha":"09/02/2016 11:00:57","trama":"Trama Normal","vel":"0","lat":"-12.05444","lng":"-76.97194"},{"id":"48","name":"5026C","markerimage":"imagen/bus_taller_rtx.png","ruta":"______","nocupa":"49","tocupa":"0","tlibres":"49","fecha":"15/02/2016 16:21:12","trama":"Taller Sta Anita","vel":"0","lat":"-12.055","lng":"-76.9712"},{"id":"49","name":"4022C","markerimage":"imagen/bus_taller.png","ruta":"______","nocupa":"62","tocupa":"0","tlibres":"62","fecha":"29/03/2016 15:43:08","trama":"Taller Sta Anita","vel":"0","lat":"-12.05444","lng":"-76.97167"},{"id":"50","name":"4016C","markerimage":"imagen/bus_taller.png","ruta":"______","nocupa":"62","tocupa":"0","tlibres":"62","fecha":"29/03/2016 15:43:43","trama":"Taller Sta Anita","vel":"0","lat":"-12.055","lng":"-76.97139"},{"id":"51","name":"4018C","markerimage":"imagen/bus_taller.png","ruta":"______","nocupa":"62","tocupa":"0","tlibres":"62","fecha":"29/03/2016 15:43:13","trama":"Taller Sta Anita","vel":"0","lat":"-12.05444","lng":"-76.97167"},{"id":"52","name":"6028C","markerimage":"imagen/bus_taller.png","ruta":"______","nocupa":"0","tocupa":"0","tlibres":"0","fecha":"29/03/2016 15:40:42","trama":"Taller Sta Anita","vel":"0","lat":"-12.0544","lng":"-76.97122"},{"id":"53","name":"7018C","markerimage":"imagen/busde_age_rtx.png","ruta":"CHILIM","nocupa":"39","tocupa":"34","tlibres":"5","fecha":"29/03/2016 11:39:44","trama":"Terminal Chiclayo","vel":"0","lat":"-6.77611","lng":"-79.83694"},{"id":"54","name":"7026C","markerimage":"imagen/bus_nolimde_rtx.png","ruta":"AQPCVM","nocupa":"39","tocupa":"0","tlibres":"39","fecha":"21/03/2016 10:23:56","trama":"Trama Normal","vel":"0","lat":"-16.40833","lng":"-71.55222"},{"id":"55","name":"8020C","markerimage":"imagen/busde_age.png","ruta":"ILOLIM","nocupa":"52","tocupa":"26","tlibres":"26","fecha":"29/03/2016 15:39:45","trama":"Ag.ilo","vel":"0","lat":"-17.64639","lng":"-71.34694"},{"id":"56","name":"7022C","markerimage":"imagen/busde_age.png","ruta":"QOSAQP","nocupa":"39","tocupa":"27","tlibres":"12","fecha":"29/03/2016 15:40:06","trama":"Terminal Cusco (nvo)","vel":"0","lat":"-13.53335","lng":"-71.96884"},{"id":"57","name":"7020C","markerimage":"imagen/bus_taller.png","ruta":"______","nocupa":"39","tocupa":"0","tlibres":"39","fecha":"29/03/2016 15:30:42","trama":"Taller Tacna","vel":"0","lat":"-18.00556","lng":"-70.25917"},{"id":"58","name":"8074C","markerimage":"imagen/busde_age.png","ruta":"TALLIM","nocupa":"52","tocupa":"35","tlibres":"17","fecha":"29/03/2016 15:42:42","trama":"Ag.talara","vel":"0","lat":"-4.58694","lng":"-81.26972"},{"id":"59","name":"8100C","markerimage":"imagen/busiz_ret.png","ruta":"NAZLIM","nocupa":"49","tocupa":"24","tlibres":"25","fecha":"29/03/2016 15:43:01","trama":"Trama Normal","vel":"87","lat":"-14.76306","lng":"-75.04611"},{"id":"60","name":"8048C","markerimage":"imagen/bus_nolimiz.png","ruta":"PUNAQP","nocupa":"52","tocupa":"31","tlibres":"21","fecha":"29/03/2016 15:39:57","trama":"Trama Normal","vel":"87","lat":"-15.68528","lng":"-70.07111"},{"id":"61","name":"8006C","markerimage":"imagen/bus_taller.png","ruta":"LIMHUZ","nocupa":"52","tocupa":"30","tlibres":"22","fecha":"29/03/2016 15:42:56","trama":"Taller Sta Anita","vel":"0","lat":"-12.055","lng":"-76.97194"},{"id":"62","name":"7106C","markerimage":"imagen/bus_sprg.png","ruta":"______","nocupa":"39","tocupa":"0","tlibres":"39","fecha":"29/03/2016 15:36:32","trama":"Trama Normal","vel":"0","lat":"-13.53306","lng":"-71.94972"},{"id":"63","name":"7112C","markerimage":"imagen/bus_taller.png","ruta":"LIMQOS","nocupa":"39","tocupa":"18","tlibres":"21","fecha":"29/03/2016 15:43:16","trama":"Taller Sta Anita","vel":"0","lat":"-12.05528","lng":"-76.97222"},{"id":"64","name":"8086C","markerimage":"imagen/busde.png","ruta":"LIMNAZ","nocupa":"52","tocupa":"27","tlibres":"25","fecha":"29/03/2016 15:42:47","trama":"Trama Normal","vel":"89","lat":"-12.89194","lng":"-76.50833"},{"id":"65","name":"8052C","markerimage":"imagen/busde_age.png","ruta":"PUNAQP","nocupa":"52","tocupa":"16","tlibres":"36","fecha":"29/03/2016 15:42:41","trama":"Ag.puno","vel":"0","lat":"-15.84333","lng":"-70.01639"},{"id":"66","name":"8058C","markerimage":"imagen/bus_taller.png","ruta":"LIMSUL","nocupa":"52","tocupa":"15","tlibres":"37","fecha":"29/03/2016 15:43:04","trama":"Taller Sta Anita","vel":"0","lat":"-12.05528","lng":"-76.97222"},{"id":"67","name":"8050C","markerimage":"imagen/bus_taller.png","ruta":"AQPLIM","nocupa":"52","tocupa":"39","tlibres":"13","fecha":"29/03/2016 15:39:40","trama":"Taller Arequipa","vel":"0","lat":"-16.40722","lng":"-71.56111"},{"id":"68","name":"8068C","markerimage":"imagen/busde_age.png","ruta":"LIMPIU","nocupa":"52","tocupa":"22","tlibres":"30","fecha":"29/03/2016 15:42:27","trama":"Terminal Plaza Lima Norte","vel":"23","lat":"-12.00639","lng":"-77.05639"},{"id":"69","name":"8062C","markerimage":"imagen/bus_taller.png","ruta":"______","nocupa":"52","tocupa":"0","tlibres":"52","fecha":"29/03/2016 15:39:50","trama":"Taller Sta Anita","vel":"0","lat":"-12.05472","lng":"-76.97056"},{"id":"70","name":"8060C","markerimage":"imagen/bus_taller.png","ruta":"______","nocupa":"52","tocupa":"0","tlibres":"52","fecha":"29/03/2016 15:43:06","trama":"Taller Sta Anita","vel":"0","lat":"-12.05528","lng":"-76.97194"},{"id":"71","name":"7064C","markerimage":"imagen/bus_taller.png","ruta":"LIMTAC","nocupa":"39","tocupa":"39","tlibres":"0","fecha":"29/03/2016 15:43:14","trama":"Taller Sta Anita","vel":"0","lat":"-12.05528","lng":"-76.97222"},{"id":"72","name":"8018C","markerimage":"imagen/bus_taller.png","ruta":"LIMAQP","nocupa":"52","tocupa":"19","tlibres":"33","fecha":"29/03/2016 15:43:08","trama":"Taller Sta Anita","vel":"0","lat":"-12.05528","lng":"-76.9725"},{"id":"73","name":"7066C","markerimage":"imagen/bus_taller.png","ruta":"LIMAYA","nocupa":"39","tocupa":"18","tlibres":"21","fecha":"29/03/2016 15:34:48","trama":"Taller Sta Anita","vel":"0","lat":"-12.055","lng":"-76.97167"},{"id":"74","name":"7068C","markerimage":"imagen/bus_taller.png","ruta":"LIMAQP","nocupa":"39","tocupa":"16","tlibres":"23","fecha":"29/03/2016 15:39:10","trama":"Taller Sta Anita","vel":"0","lat":"-12.05472","lng":"-76.97111"},{"id":"75","name":"8064C","markerimage":"imagen/bus_taller.png","ruta":"LIMPIU","nocupa":"52","tocupa":"24","tlibres":"28","fecha":"29/03/2016 15:39:41","trama":"Taller Sta Anita","vel":"0","lat":"-12.055","lng":"-76.97194"},{"id":"76","name":"7036C","markerimage":"imagen/busiz.png","ruta":"LIMTRU","nocupa":"39","tocupa":"27","tlibres":"12","fecha":"29/03/2016 15:43:24","trama":"Trama Normal","vel":"76","lat":"-11.17389","lng":"-77.58278"},{"id":"77","name":"8012C","markerimage":"imagen/busiz_ret.png","ruta":"NAZLIM","nocupa":"52","tocupa":"32","tlibres":"20","fecha":"29/03/2016 15:43:28","trama":"Pan.sur[paracas-peaj.ica]","vel":"90","lat":"-13.91167","lng":"-76.01361"},{"id":"78","name":"8078C","markerimage":"imagen/busde_ret.png","ruta":"PIULIM","nocupa":"52","tocupa":"29","tlibres":"23","fecha":"29/03/2016 15:39:38","trama":"Trama Normal","vel":"83","lat":"-5.48639","lng":"-80.60028"},{"id":"79","name":"8092C","markerimage":"imagen/busiz.png","ruta":"LIMTAL","nocupa":"52","tocupa":"35","tlibres":"17","fecha":"29/03/2016 15:39:41","trama":"Lima/av.nicolas Arriola","vel":"10","lat":"-12.08583","lng":"-77.01528"},{"id":"80","name":"8026C","markerimage":"imagen/busde.png","ruta":"LIMAQP","nocupa":"52","tocupa":"35","tlibres":"17","fecha":"29/03/2016 15:39:29","trama":"Trama Normal","vel":"39","lat":"-12.03472","lng":"-77.00944"},{"id":"81","name":"7016C","markerimage":"imagen/busiz_ret.png","ruta":"ICALIM","nocupa":"39","tocupa":"19","tlibres":"20","fecha":"29/03/2016 15:39:35","trama":"Trama Normal","vel":"4","lat":"-12.11083","lng":"-76.97806"},{"id":"82","name":"7118C","markerimage":"imagen/busde.png","ruta":"LIMHUN","nocupa":"39","tocupa":"27","tlibres":"12","fecha":"29/03/2016 15:43:12","trama":"Trama Normal","vel":"79","lat":"-11.98903","lng":"-75.28883"},{"id":"83","name":"8128C","markerimage":"imagen/bus_sprg.png","ruta":"______","nocupa":"52","tocupa":"0","tlibres":"52","fecha":"29/03/2016 15:39:08","trama":"Trama Normal","vel":"0","lat":"-13.15639","lng":"-74.22861"},{"id":"84","name":"8082C","markerimage":"imagen/bus_nolimde_rtx.png","ruta":"AQPPUN","nocupa":"52","tocupa":"19","tlibres":"33","fecha":"29/03/2016 15:09:40","trama":"Trama Normal","vel":"46","lat":"-16.20944","lng":"-71.65278"},{"id":"85","name":"8099C","markerimage":"imagen/bus_taller.png","ruta":"______","nocupa":"52","tocupa":"0","tlibres":"52","fecha":"29/03/2016 15:39:49","trama":"Taller Sta Anita","vel":"0","lat":"-12.055","lng":"-76.97167"},{"id":"86","name":"7054C","markerimage":"imagen/busde_retx.png","ruta":"LIMHUN","nocupa":"39","tocupa":"17","tlibres":"22","fecha":"29/03/2016 15:22:02","trama":"Trama Normal","vel":"49","lat":"-11.92583","lng":"-76.64472"},{"id":"87","name":"7060C","markerimage":"imagen/bus_taller.png","ruta":"LIMCHI","nocupa":"39","tocupa":"12","tlibres":"27","fecha":"29/03/2016 15:39:04","trama":"Taller Sta Anita","vel":"0","lat":"-12.05444","lng":"-76.97083"},{"id":"88","name":"7052C","markerimage":"imagen/bus_taller.png","ruta":"______","nocupa":"39","tocupa":"0","tlibres":"39","fecha":"29/03/2016 15:39:34","trama":"Taller Ruiseñores","vel":"0","lat":"-12.0525","lng":"-76.96778"},{"id":"89","name":"7040C","markerimage":"imagen/busde_age.png","ruta":"QOSPMA","nocupa":"39","tocupa":"11","tlibres":"28","fecha":"29/03/2016 15:39:36","trama":"Terminal Cusco (nvo)","vel":"0","lat":"-13.53333","lng":"-71.96861"},{"id":"90","name":"8066C","markerimage":"imagen/bus_taller.png","ruta":"AQPQOS","nocupa":"52","tocupa":"25","tlibres":"27","fecha":"29/03/2016 15:39:06","trama":"Taller Arequipa","vel":"0","lat":"-16.40694","lng":"-71.56111"},{"id":"91","name":"8088C","markerimage":"imagen/bus_taller.png","ruta":"______","nocupa":"52","tocupa":"0","tlibres":"52","fecha":"29/03/2016 15:39:49","trama":"Taller Sta Anita","vel":"0","lat":"-12.055","lng":"-76.97194"},{"id":"92","name":"8076C","markerimage":"imagen/busde_ret.png","ruta":"TRULIM","nocupa":"52","tocupa":"30","tlibres":"22","fecha":"29/03/2016 15:43:01","trama":"Trama Normal","vel":"0","lat":"-8.10389","lng":"-79.02389"},{"id":"93","name":"8090C","markerimage":"imagen/busde.png","ruta":"LIMNAZ","nocupa":"52","tocupa":"14","tlibres":"38","fecha":"29/03/2016 15:42:55","trama":"Trama Normal","vel":"88","lat":"-13.1325","lng":"-76.39056"},{"id":"94","name":"8094C","markerimage":"imagen/bus_taller.png","ruta":"______","nocupa":"52","tocupa":"0","tlibres":"52","fecha":"29/03/2016 15:43:12","trama":"Taller Sta Anita","vel":"0","lat":"-12.055","lng":"-76.9725"},{"id":"95","name":"8042C","markerimage":"imagen/busde_age.png","ruta":"HUZLIM","nocupa":"52","tocupa":"39","tlibres":"13","fecha":"29/03/2016 15:39:17","trama":"Ag.huaraz","vel":"0","lat":"-9.5275","lng":"-77.52722"},{"id":"96","name":"7048C","markerimage":"imagen/busde_ret.png","ruta":"AQPLIM","nocupa":"39","tocupa":"33","tlibres":"6","fecha":"29/03/2016 15:43:11","trama":"Terrapuerto Aqp","vel":"0","lat":"-16.42389","lng":"-71.54556"},{"id":"97","name":"7058C","markerimage":"imagen/busde_ret.png","ruta":"HUNLIM","nocupa":"39","tocupa":"27","tlibres":"12","fecha":"29/03/2016 15:41:55","trama":"Lima/av.nicolas Arriola","vel":"0","lat":"-12.08361","lng":"-77.01417"},{"id":"98","name":"7044C","markerimage":"imagen/busde_ret.png","ruta":"TRULIM","nocupa":"39","tocupa":"35","tlibres":"4","fecha":"29/03/2016 15:39:50","trama":"Trama Normal","vel":"0","lat":"-8.10389","lng":"-79.02389"},{"id":"99","name":"8084C","markerimage":"imagen/busde_ret.png","ruta":"SULLIM","nocupa":"52","tocupa":"31","tlibres":"21","fecha":"29/03/2016 15:42:42","trama":"Trama Normal","vel":"0","lat":"-4.90917","lng":"-80.69806"},{"id":"100","name":"7038C","markerimage":"imagen/busde.png","ruta":"LIMNAZ","nocupa":"39","tocupa":"30","tlibres":"9","fecha":"29/03/2016 15:42:31","trama":"Trama Normal","vel":"28","lat":"-13.41472","lng":"-76.14667"},{"id":"101","name":"8072C","markerimage":"imagen/bus_taller.png","ruta":"______","nocupa":"52","tocupa":"0","tlibres":"52","fecha":"29/03/2016 15:42:23","trama":"Taller Sta Anita","vel":"0","lat":"-12.05472","lng":"-76.97167"},{"id":"102","name":"8098C","markerimage":"imagen/bus_taller.png","ruta":"______","nocupa":"52","tocupa":"0","tlibres":"52","fecha":"29/03/2016 15:42:30","trama":"Taller Arequipa","vel":"1","lat":"-16.40694","lng":"-71.56111"},{"id":"103","name":"7050C","markerimage":"imagen/bus_taller.png","ruta":"LIMHUN","nocupa":"39","tocupa":"26","tlibres":"13","fecha":"29/03/2016 15:43:16","trama":"Taller Sta Anita","vel":"0","lat":"-12.05444","lng":"-76.97139"},{"id":"104","name":"7062C","markerimage":"imagen/busiz_ret.png","ruta":"HUNLIM","nocupa":"39","tocupa":"36","tlibres":"3","fecha":"29/03/2016 15:42:20","trama":"Trama Normal","vel":"53","lat":"-11.78722","lng":"-75.57694"},{"id":"105","name":"7046C","markerimage":"imagen/bus_sprg.png","ruta":"______","nocupa":"39","tocupa":"0","tlibres":"39","fecha":"29/03/2016 15:42:24","trama":"Trama Normal","vel":"0","lat":"-13.15639","lng":"-74.22861"},{"id":"106","name":"7056C","markerimage":"imagen/bus_taller.png","ruta":"AQPQOS","nocupa":"39","tocupa":"31","tlibres":"8","fecha":"29/03/2016 15:43:01","trama":"Taller Arequipa","vel":"1","lat":"-16.40722","lng":"-71.56111"},{"id":"107","name":"8054C","markerimage":"imagen/bus_taller.png","ruta":"LIMTRU","nocupa":"52","tocupa":"16","tlibres":"36","fecha":"29/03/2016 15:42:40","trama":"Taller Sta Anita","vel":"2","lat":"-12.055","lng":"-76.97222"},{"id":"108","name":"8056C","markerimage":"imagen/busiz.png","ruta":"LIMSUL","nocupa":"52","tocupa":"50","tlibres":"2","fecha":"29/03/2016 15:39:08","trama":"Trama Normal","vel":"86","lat":"-5.13278","lng":"-80.7"},{"id":"109","name":"8070C","markerimage":"imagen/busde.png","ruta":"LIMAQP","nocupa":"52","tocupa":"49","tlibres":"3","fecha":"29/03/2016 15:39:22","trama":"Trama Normal","vel":"22","lat":"-12.08444","lng":"-77.00556"},{"id":"110","name":"8080C","markerimage":"imagen/busiz_ret.png","ruta":"AQPLIM","nocupa":"52","tocupa":"29","tlibres":"23","fecha":"29/03/2016 15:34:58","trama":"Trama Normal","vel":"73","lat":"-16.42639","lng":"-72.26028"},{"id":"111","name":"8022C","markerimage":"imagen/busde_ret.png","ruta":"CHILIM","nocupa":"52","tocupa":"41","tlibres":"11","fecha":"29/03/2016 15:39:25","trama":"Trama Normal","vel":"72","lat":"-9.46472","lng":"-78.32139"},{"id":"112","name":"8024C","markerimage":"imagen/busde_age.png","ruta":"LIMCHI","nocupa":"52","tocupa":"35","tlibres":"17","fecha":"29/03/2016 15:39:50","trama":"Terminal Chimbote","vel":"0","lat":"-9.105","lng":"-78.55917"},{"id":"113","name":"7042C","markerimage":"imagen/bus_taller.png","ruta":"______","nocupa":"39","tocupa":"0","tlibres":"39","fecha":"29/03/2016 15:39:45","trama":"Taller Arequipa","vel":"0","lat":"-16.40722","lng":"-71.56083"},{"id":"114","name":"8002C","markerimage":"imagen/busde.png","ruta":"LIMAQP","nocupa":"52","tocupa":"36","tlibres":"16","fecha":"29/03/2016 15:35:14","trama":"Trama Normal","vel":"90","lat":"-15.44174","lng":"-74.87135"},{"id":"115","name":"8028C","markerimage":"imagen/busiz_ret.png","ruta":"AQPLIM","nocupa":"52","tocupa":"22","tlibres":"30","fecha":"29/03/2016 15:39:58","trama":"Trama Normal","vel":"30","lat":"-16.4575","lng":"-71.95444"},{"id":"116","name":"8030C","markerimage":"imagen/bus_taller.png","ruta":"AQPLIM","nocupa":"52","tocupa":"44","tlibres":"8","fecha":"29/03/2016 15:39:25","trama":"Taller Sta Anita","vel":"0","lat":"-12.05444","lng":"-76.97139"},{"id":"117","name":"8032C","markerimage":"imagen/bus_taller.png","ruta":"______","nocupa":"52","tocupa":"0","tlibres":"52","fecha":"29/03/2016 15:39:22","trama":"Taller Ruiseñores","vel":"0","lat":"-12.05222","lng":"-76.9675"},{"id":"118","name":"4112C","markerimage":"imagen/busde_ret.png","ruta":"ICALIM","nocupa":"0","tocupa":"44","tlibres":"-44","fecha":"29/03/2016 15:40:46","trama":"Trama Normal","vel":"18","lat":"-13.4492","lng":"-76.13598"},{"id":"119","name":"4100C","markerimage":"imagen/bus_taller.png","ruta":"LIMICA","nocupa":"0","tocupa":"6","tlibres":"-6","fecha":"29/03/2016 15:40:48","trama":"Taller Sta Anita","vel":"0","lat":"-12.05503","lng":"-76.97159"},{"id":"120","name":"8034C","markerimage":"imagen/bus_sprg.png","ruta":"______","nocupa":"52","tocupa":"0","tlibres":"52","fecha":"29/03/2016 15:39:12","trama":"Trama Normal","vel":"0","lat":"-13.15667","lng":"-74.22861"},{"id":"121","name":"8036C","markerimage":"imagen/busde_age.png","ruta":"PUNQOS","nocupa":"52","tocupa":"38","tlibres":"14","fecha":"29/03/2016 15:39:38","trama":"Ag.puno","vel":"0","lat":"-15.84333","lng":"-70.01639"},{"id":"122","name":"8038C","markerimage":"imagen/bus_nolimiz.png","ruta":"QOSPUN","nocupa":"52","tocupa":"27","tlibres":"25","fecha":"29/03/2016 15:39:45","trama":"Trama Normal","vel":"0","lat":"-13.53361","lng":"-71.96861"},{"id":"123","name":"8040C","markerimage":"imagen/busde_ret.png","ruta":"PIULIM","nocupa":"52","tocupa":"35","tlibres":"17","fecha":"29/03/2016 15:39:36","trama":"Trama Normal","vel":"0","lat":"-5.2","lng":"-80.62639"},{"id":"124","name":"8044C","markerimage":"imagen/bus_taller.png","ruta":"______","nocupa":"52","tocupa":"0","tlibres":"52","fecha":"29/03/2016 15:40:11","trama":"Taller Sta Anita","vel":"0","lat":"-12.05464","lng":"-76.97169"},{"id":"125","name":"7102C","markerimage":"imagen/bus_taller.png","ruta":"LIMHUN","nocupa":"39","tocupa":"32","tlibres":"7","fecha":"29/03/2016 15:43:10","trama":"Taller Sta Anita","vel":"0","lat":"-12.05497","lng":"-76.97193"},{"id":"126","name":"8046C","markerimage":"imagen/bus_taller.png","ruta":"AQPLIM","nocupa":"52","tocupa":"25","tlibres":"27","fecha":"29/03/2016 15:39:57","trama":"Taller Arequipa","vel":"0","lat":"-16.40694","lng":"-71.56139"},{"id":"127","name":"3032I","markerimage":"imagen/busde_ret_tx.png","ruta":"BOGLIM","nocupa":"46","tocupa":"46","tlibres":"0","fecha":"29/03/2016 15:26:45","trama":"Trama Normal","vel":"65","lat":"0.57722","lng":"-77.95139"},{"id":"128","name":"3034I","markerimage":"imagen/busiz_ret.png","ruta":"SCLLIM","nocupa":"46","tocupa":"38","tlibres":"8","fecha":"29/03/2016 15:40:01","trama":"Trama Normal","vel":"90","lat":"-17.77194","lng":"-70.74444"},{"id":"129","name":"3016I","markerimage":"imagen/busde_ret.png","ruta":"SCLLIM","nocupa":"46","tocupa":"29","tlibres":"17","fecha":"29/03/2016 15:29:52","trama":"Trama Normal","vel":"84","lat":"-29.09472","lng":"-70.91861"},{"id":"130","name":"3018I","markerimage":"imagen/bus_taller.png","ruta":"LIMBSA","nocupa":"46","tocupa":"46","tlibres":"0","fecha":"29/03/2016 15:39:13","trama":"Taller Sta Anita","vel":"0","lat":"-12.05528","lng":"-76.97222"},{"id":"131","name":"3020I","markerimage":"imagen/bus_sprg_rtx.png","ruta":"______","nocupa":"46","tocupa":"0","tlibres":"46","fecha":"14/03/2016 15:23:30","trama":"Trama Normal","vel":"0","lat":"-24.27667","lng":"-65.19917"},{"id":"132","name":"3022I","markerimage":"imagen/busiz.png","ruta":"LIMBSA","nocupa":"46","tocupa":"46","tlibres":"0","fecha":"29/03/2016 15:39:02","trama":"Trama Normal","vel":"3","lat":"-14.06417","lng":"-75.73583"},{"id":"133","name":"3024I","markerimage":"imagen/busde.png","ruta":"LIMSCL","nocupa":"46","tocupa":"46","tlibres":"0","fecha":"29/03/2016 15:39:14","trama":"Trama Normal","vel":"52","lat":"-14.19028","lng":"-75.71444"},{"id":"134","name":"3026I","markerimage":"imagen/busde_retx.png","ruta":"LIMSCL","nocupa":"46","tocupa":"45","tlibres":"1","fecha":"29/03/2016 15:08:15","trama":"Trama Normal","vel":"93","lat":"-21.03278","lng":"-69.63028"},{"id":"135","name":"3028I","markerimage":"imagen/bus_taller.png","ruta":"BSALIM","nocupa":"46","tocupa":"36","tlibres":"10","fecha":"29/03/2016 15:39:18","trama":"Taller Sta Anita","vel":"0","lat":"-12.05472","lng":"-76.97167"},{"id":"136","name":"3030I","markerimage":"imagen/busde.png","ruta":"LIMSCL","nocupa":"46","tocupa":"46","tlibres":"0","fecha":"29/03/2016 15:35:45","trama":"Trama Normal","vel":"0","lat":"-33.44667","lng":"-70.70222"},{"id":"137","name":"3036I","markerimage":"imagen/busiz_ret.png","ruta":"BSALIM","nocupa":"46","tocupa":"26","tlibres":"20","fecha":"29/03/2016 15:39:23","trama":"Trama Normal","vel":"90","lat":"-32.64528","lng":"-62.20528"},{"id":"138","name":"3038I","markerimage":"imagen/bus_taller.png","ruta":"______","nocupa":"46","tocupa":"0","tlibres":"46","fecha":"29/03/2016 15:39:48","trama":"Taller Sta Anita","vel":"0","lat":"-12.05528","lng":"-76.97222"},{"id":"139","name":"3040I","markerimage":"imagen/busiz_ret_tx.png","ruta":"BSALIM","nocupa":"46","tocupa":"14","tlibres":"32","fecha":"29/03/2016 15:27:22","trama":"Trama Normal","vel":"90","lat":"-33.08361","lng":"-60.6325"},{"id":"140","name":"8144C","markerimage":"imagen/bus_taller.png","ruta":"______","nocupa":"52","tocupa":"0","tlibres":"52","fecha":"29/03/2016 15:43:19","trama":"Taller Sta Anita","vel":"0","lat":"-12.055","lng":"-76.97194"},{"id":"141","name":"8146C","markerimage":"imagen/bus_taller.png","ruta":"______","nocupa":"52","tocupa":"0","tlibres":"52","fecha":"29/03/2016 15:43:47","trama":"Taller Sta Anita","vel":"0","lat":"-12.055","lng":"-76.97167"},{"id":"142","name":"7070C","markerimage":"imagen/bus_taller.png","ruta":"LIMHUN","nocupa":"39","tocupa":"35","tlibres":"4","fecha":"29/03/2016 15:43:27","trama":"Taller Ruiseñores","vel":"0","lat":"-12.0525","lng":"-76.9675"},{"id":"143","name":"7072C","markerimage":"imagen/busiz_ret.png","ruta":"NAZLIM","nocupa":"39","tocupa":"15","tlibres":"24","fecha":"29/03/2016 15:42:56","trama":"Trama Normal","vel":"51","lat":"-13.32222","lng":"-76.24333"},{"id":"144","name":"AJ753","markerimage":"imagen/bus_sprg.png","ruta":"______","nocupa":"0","tocupa":"0","tlibres":"0","fecha":"29/03/2016 15:43:11","trama":"Trama Normal","vel":"0","lat":"-14.86611","lng":"-71.32528"},{"id":"145","name":"8120C","markerimage":"imagen/bus_taller.png","ruta":"LIMHUN","nocupa":"52","tocupa":"17","tlibres":"35","fecha":"29/03/2016 15:39:24","trama":"Taller Sta Anita","vel":"0","lat":"-12.05444","lng":"-76.97111"},{"id":"146","name":"7116C","markerimage":"imagen/bus_taller.png","ruta":"LIMHUN","nocupa":"39","tocupa":"35","tlibres":"4","fecha":"29/03/2016 15:39:51","trama":"Taller Sta Anita","vel":"0","lat":"-12.055","lng":"-76.97194"},{"id":"147","name":"8096C","markerimage":"imagen/bus_taller.png","ruta":"______","nocupa":"52","tocupa":"0","tlibres":"52","fecha":"29/03/2016 15:39:12","trama":"Taller Sta Anita","vel":"0","lat":"-12.05472","lng":"-76.97139"},{"id":"148","name":"BBP02","markerimage":"imagen/bus_sprg.png","ruta":"______","nocupa":"0","tocupa":"0","tlibres":"0","fecha":"29/03/2016 15:37:34","trama":"Trama Normal","vel":"38","lat":"-11.595","lng":"-76.19056"},{"id":"149","name":"8140C","markerimage":"imagen/bus_sprg.png","ruta":"______","nocupa":"52","tocupa":"0","tlibres":"52","fecha":"29/03/2016 15:43:37","trama":"Trama Normal","vel":"12","lat":"-12.065","lng":"-76.99028"},{"id":"150","name":"7104C","markerimage":"imagen/bus_taller.png","ruta":"LIMAQP","nocupa":"39","tocupa":"13","tlibres":"26","fecha":"29/03/2016 15:40:15","trama":"Taller Sta Anita","vel":"0","lat":"-12.05497","lng":"-76.97206"},{"id":"151","name":"7100C","markerimage":"imagen/bus_taller.png","ruta":"______","nocupa":"39","tocupa":"0","tlibres":"39","fecha":"29/03/2016 15:43:58","trama":"Taller Ruiseñores","vel":"0","lat":"-12.05223","lng":"-76.96757"},{"id":"152","name":"7122C","markerimage":"imagen/bus_taller.png","ruta":"______","nocupa":"39","tocupa":"0","tlibres":"39","fecha":"29/03/2016 15:43:44","trama":"Taller Tacna","vel":"0","lat":"-18.00547","lng":"-70.25897"},{"id":"153","name":"3042I","markerimage":"imagen/busde_retx.png","ruta":"LIMBSA","nocupa":"46","tocupa":"40","tlibres":"6","fecha":"29/03/2016 15:23:42","trama":"Trama Normal","vel":"91","lat":"-34.05028","lng":"-59.31667"},{"id":"154","name":"7124C","markerimage":"imagen/busde_ret.png","ruta":"TACLIM","nocupa":"39","tocupa":"27","tlibres":"12","fecha":"29/03/2016 15:43:49","trama":"Trama Normal","vel":"56","lat":"-17.1922","lng":"-70.95117"},{"id":"155","name":"3044I","markerimage":"imagen/bus_taller.png","ruta":"______","nocupa":"46","tocupa":"0","tlibres":"46","fecha":"29/03/2016 15:39:00","trama":"Taller Sta Anita","vel":"0","lat":"-12.055","lng":"-76.97167"},{"id":"156","name":"7126C","markerimage":"imagen/busde_age.png","ruta":"HUNLIM","nocupa":"39","tocupa":"21","tlibres":"18","fecha":"29/03/2016 15:42:53","trama":"Ag.huancayo(ferrocarril)","vel":"0","lat":"-12.0601","lng":"-75.20917"},{"id":"157","name":"7120C","markerimage":"imagen/bus_taller_rtx.png","ruta":"AQPLIM","nocupa":"39","tocupa":"10","tlibres":"29","fecha":"29/03/2016 15:24:52","trama":"Taller Arequipa","vel":"0","lat":"-16.40722","lng":"-71.56111"},{"id":"158","name":"7114C","markerimage":"imagen/busiz_ret.png","ruta":"QOSLIM","nocupa":"39","tocupa":"35","tlibres":"4","fecha":"29/03/2016 15:37:00","trama":"Trama Normal","vel":"65","lat":"-13.44663","lng":"-72.3875"},{"id":"159","name":"7110C","markerimage":"imagen/busde_ret.png","ruta":"QOSLIM","nocupa":"39","tocupa":"38","tlibres":"1","fecha":"29/03/2016 15:39:51","trama":"Trama Normal","vel":"0","lat":"-13.53333","lng":"-71.96889"},{"id":"160","name":"8008C","markerimage":"imagen/bus_taller.png","ruta":"AQPICA","nocupa":"52","tocupa":"32","tlibres":"20","fecha":"29/03/2016 15:43:03","trama":"Taller Arequipa","vel":"0","lat":"-16.40722","lng":"-71.56139"},{"id":"161","name":"4102C","markerimage":"imagen/busiz.png","ruta":"LIMICA","nocupa":"0","tocupa":"16","tlibres":"-16","fecha":"29/03/2016 15:40:45","trama":"Trama Normal","vel":"48","lat":"-13.67304","lng":"-76.15702"},{"id":"162","name":"4104C","markerimage":"imagen/busde.png","ruta":"LIMICA","nocupa":"0","tocupa":"12","tlibres":"-12","fecha":"29/03/2016 15:40:38","trama":"Trama Normal","vel":"87","lat":"-12.89376","lng":"-76.50738"},{"id":"163","name":"4110C","markerimage":"imagen/busde_age.png","ruta":"ICALIM","nocupa":"0","tocupa":"21","tlibres":"-21","fecha":"29/03/2016 15:40:19","trama":"Ag.ica","vel":"0","lat":"-14.06394","lng":"-75.73396"},{"id":"164","name":"4114C","markerimage":"imagen/busde.png","ruta":"LIMICA","nocupa":"0","tocupa":"18","tlibres":"-18","fecha":"29/03/2016 15:40:30","trama":"Trama Normal","vel":"5","lat":"-12.06568","lng":"-76.98746"},{"id":"165","name":"4116C","markerimage":"imagen/busde_age.png","ruta":"ICALIM","nocupa":"0","tocupa":"14","tlibres":"-14","fecha":"29/03/2016 15:40:14","trama":"Ag.ica","vel":"0","lat":"-14.06414","lng":"-75.73384"},{"id":"166","name":"4118C","markerimage":"imagen/bus_taller.png","ruta":"LIMICA","nocupa":"0","tocupa":"4","tlibres":"-4","fecha":"29/03/2016 15:40:00","trama":"Taller Sta Anita","vel":"0","lat":"-12.05514","lng":"-76.97196"},{"id":"167","name":"4120C","markerimage":"imagen/busiz_ret.png","ruta":"ICALIM","nocupa":"0","tocupa":"13","tlibres":"-13","fecha":"29/03/2016 15:40:38","trama":"Trama Normal","vel":"90","lat":"-13.93486","lng":"-75.86609"}]}